{"forked_repos": ["deepcut", "neuroSummerSchools", "tutorials"], "num_watches": 151, "num_followers": 88, "hireable": null, "num_forked_repos": 3, "num_public_gists": 52, "languages": {"JavaScript": 2, "Python": 24, "Mathematica": 1, "TeX": 2, "Jupyter Notebook": 2, "HTML": 1, "null": 3}, "location": "Philadelphia, PA", "email": null, "bio": "Science of Science research @KordingLab, Former intern at @allenai ", "num_stars": 151, "company": "University of Pennsylvania", "num_pulls": 0, "html_url": "https://github.com/titipata", "num_owned_repos": 32, "owned_repos": ["affiliation_parser", "affilparser", "arxivpy", "bangkok_transit", "be566_network_neuroscience", "bme469_neural_control_of_movement", "cooccurence", "customize_ipython_notebook", "forecast", "gillespie", "google_scholar_scoreboard", "grant_database", "keyphrase_extraction", "me454_nonlinear_optimal_control", "nih_grid_matching", "paper_reviewer_matcher", "pathology_extractor", "pubmed_parser", "random_commands", "science_concierge", "science_concierge_manuscript", "scrape_google_scholar", "search_result_relevant", "talkingdata", "titipata.github.io", "titipat_cv", "touchbar-example", "visualize_line_chat", "vpca", "vuejs_examples", "wos_parser", "yelp_dataset_challenge"], "num_commits": 0, "num_public_repos": 35, "name": "Titipat Achakulvisut", "update_at": "2017-10-17T19:46:36Z", "avatar_url": "https://avatars0.githubusercontent.com/u/8295838?v=4", "login": "titipata", "num_following": 166}